argset/__init__.py
argset/py.typed
argset-0.1.1.dist-info/METADATA
argset-0.1.1.dist-info/WHEEL
argset-0.1.1.dist-info/licenses/LICENSE
argset-0.1.1.dist-info/RECORD
