Metadata-Version: 2.3
Name: argset
Version: 0.1.1
Summary: Simple callable argument inspection & filtering
Project-URL: Source Code, https://github.com/jwodder/argset
Project-URL: Bug Tracker, https://github.com/jwodder/argset/issues
Author-email: John Thorvald Wodder II <argset@varonathe.org>
License: MIT
Keywords: arguments,callable,inspect,keyword arguments,signature
Classifier: Intended Audience :: Developers
Classifier: License :: OSI Approved :: MIT License
Classifier: Programming Language :: Python :: 3
Classifier: Programming Language :: Python :: 3 :: Only
Classifier: Programming Language :: Python :: 3.8
Classifier: Programming Language :: Python :: 3.9
Classifier: Programming Language :: Python :: 3.10
Classifier: Programming Language :: Python :: 3.11
Classifier: Programming Language :: Python :: 3.12
Classifier: Programming Language :: Python :: 3.13
Classifier: Programming Language :: Python :: Implementation :: CPython
Classifier: Programming Language :: Python :: Implementation :: PyPy
Classifier: Topic :: Software Development :: Disassemblers
Classifier: Typing :: Typed
Requires-Python: >=3.8
